pyhelios/__init__.py
pyhelios/coverage.py
pyhelios/documentation.py
pyhelios/exe.py
pyhelios/highlight.py
pyhelios/plot.py
pyhelios/pyhls.py
pyhelios/python.py
pyhelios/share/plot/dataset.dat
pyhelios/share/plot/dataset.toml
pyhelios/share/templates/build.ninja
pyhelios/share/templates/coverage.tex
pyhelios/share/templates/define.tex
pyhelios/share/templates/function.tex
pyhelios/share/templates/plot.tex
pyhelios/share/templates/structure.tex
pyhelios/share/templates/typedef.tex
pyhelios/template.py
pyhelios/toml.py
pyhelios/workflow.py
pyhelios-2.2.4.dist-info/entry_points.txt
pyhelios-2.2.4.dist-info/LICENSE
pyhelios-2.2.4.dist-info/WHEEL
pyhelios-2.2.4.dist-info/METADATA
pyhelios-2.2.4.dist-info/RECORD
